Metadata-Version: 2.1
Name: pybmix
Version: 0.0.1
Summary: Python Bayesian Mixtures
Home-page: https://github.com/bayesmix-dev/pybmix
Author: Mario Beraha
Author-email: berahamario@gmail.com
License: BSD 3-Clause
Keywords: mixture models,bayesian,nonparametrics,clustering,density
Platform: UNKNOWN
Classifier: Programming Language :: Python :: 3
Requires-Python: >=3.6
